<?xml version="1.0" encoding="UTF-8" standalone="yes"?>
<user>
    <id>2</id>
    <name>Ervin Howell</name>
    <username>Antonette</username>
    <email>Shanna@melissa.tv</email>
    <phone>010-692-6593 x09125</phone>
    <website>anastasia.net</website>
    <address>
        <city>Wisokyburgh</city>
        <geo>
            <lat>-43.9509</lat>
            <lng>-34.4618</lng>
        </geo>
        <street>Victor Plains</street>
        <suite>Suite 879</suite>
        <zipcode>90566-7771</zipcode>
    </address>
    <company>
        <bs>synergize scalable supply-chains</bs>
        <catchPhrase>Proactive didactic contingency</catchPhrase>
        <name>Deckow-Crist</name>
    </company>
</user>
